fyle_allauth/__init__.py
fyle_allauth/app_settings.py
fyle_allauth/apps.py
fyle_allauth/provider.py
fyle_allauth/tests.py
fyle_allauth/urls.py
fyle_allauth/views.py
fyle_allauth/migrations/__init__.py
fyle_django_allauth-0.1.2.dist-info/LICENSE
fyle_django_allauth-0.1.2.dist-info/METADATA
fyle_django_allauth-0.1.2.dist-info/WHEEL
fyle_django_allauth-0.1.2.dist-info/top_level.txt
fyle_django_allauth-0.1.2.dist-info/RECORD
